nimgame/__init__.py
nimgame/__main__.py
nimgame/docs/Makefile
nimgame/docs/README.rst
nimgame/docs/conf.py
nimgame/docs/index.rst
nimgame/docs/make.bat
nimgame/docs/requirements.txt
nimgame/docs/_static/srccode_width_correction.css
nimgame/docs/modules/__init__.rst
nimgame/docs/modules/calculations.rst
nimgame/docs/modules/core.rst
nimgame/docs/modules/playing.cli.ansi.rst
nimgame/docs/modules/playing.cli.play.rst
nimgame/docs/modules/playing.demo.rst
nimgame/docs/modules/playing.web.play.rst
nimgame/docs/modules/playing.web.playscript.rst
nimgame/docs/modules/tests.testruns.rst
nimgame/docs/modules/typedefs.rst
nimgame/docs/modules/version.rst
nimgame/environ/frontend/play.html
nimgame/environ/images/coinheaps.jpg
nimgame/source/__init__.py
nimgame/source/calculations.py
nimgame/source/core.py
nimgame/source/typedefs.py
nimgame/source/version.py
nimgame/source/playing/demo.py
nimgame/source/playing/cli/ansi.py
nimgame/source/playing/cli/play.py
nimgame/source/playing/cli/ptg_demo.py
nimgame/source/playing/web/play.py
nimgame/source/playing/web/playscript.py
nimgame/tests/testruns.py
nimgame-0.1.15.dist-info/entry_points.txt
nimgame-0.1.15.dist-info/LICENSE
nimgame-0.1.15.dist-info/WHEEL
nimgame-0.1.15.dist-info/METADATA
nimgame-0.1.15.dist-info/RECORD
