Metadata-Version: 2.1
Name: nimgame
Version: 0.1.15
Summary: Play the Game of Nim, interactively or using the API
Keywords: nim,game,heap,coin
Author: netcreator
Requires-Python: >=3.7
Classifier: Programming Language :: Python :: 3
Classifier: License :: OSI Approved :: MIT License
Classifier: Operating System :: OS Independent
Requires-Dist: valid8
Project-URL: Documentation, https://nimgame.readthedocs.io/en/latest/
Project-URL: Home, http://bitbucket.org/netcreator/nimgame
Project-URL: TryIt, http://donno.yet.com
